azureml/__init__.py
azureml/contrib/__init__.py
azureml/contrib/explain/__init__.py
azureml/contrib/explain/model/ThirdPartyNotice.txt
azureml/contrib/explain/model/__init__.py
azureml/contrib/explain/model/image_explainer.py
azureml/contrib/explain/model/text_explainer.py
azureml/contrib/explain/model/common/__init__.py
azureml/contrib/explain/model/common/aggregate.py
azureml/contrib/explain/model/common/image_explainer_utils.py
azureml/contrib/explain/model/common/text_explainer_utils.py
azureml/contrib/explain/model/explanation/__init__.py
azureml/contrib/explain/model/explanation/explanation.py
azureml/contrib/explain/model/explanation/explanation_client/__init__.py
azureml/contrib/explain/model/han/__init__.py
azureml/contrib/explain/model/han/han_model.py
azureml/contrib/explain/model/han/han_text_explainer.py
azureml/contrib/explain/model/lime/__init__.py
azureml/contrib/explain/model/lime/lime_explainer.py
azureml/contrib/explain/model/visualize/ExplanationDashboard.py
azureml/contrib/explain/model/visualize/ExplanationWidget.py
azureml/contrib/explain/model/visualize/__init__.py
azureml/contrib/explain/model/visualize/_version.py
azureml/contrib/explain/model/visualize/_internal/__init__.py
azureml/contrib/explain/model/visualize/_internal/constants.py
azureml/contrib/explain/model/visualize/js/microsoft_mli_widget/labextension/microsoft-mli-widget-0.1.6.tgz
azureml/contrib/explain/model/visualize/static/extension.js
azureml/contrib/explain/model/visualize/static/extension.js.map
azureml/contrib/explain/model/visualize/static/index.js
azureml/contrib/explain/model/visualize/static/index.js.map
azureml_contrib_explain_model-1.0.65.data/data/etc/jupyter/nbconfig/notebook.d/microsoft-mli-widget.json
azureml_contrib_explain_model-1.0.65.data/data/share/jupyter/lab/extensions/microsoft-mli-widget-0.1.6.tgz
azureml_contrib_explain_model-1.0.65.data/data/share/jupyter/nbextensions/microsoft-mli-widget/extension.js
azureml_contrib_explain_model-1.0.65.dist-info/DESCRIPTION.rst
azureml_contrib_explain_model-1.0.65.dist-info/LICENSE.txt
azureml_contrib_explain_model-1.0.65.dist-info/METADATA
azureml_contrib_explain_model-1.0.65.dist-info/RECORD
azureml_contrib_explain_model-1.0.65.dist-info/WHEEL
azureml_contrib_explain_model-1.0.65.dist-info/metadata.json
azureml_contrib_explain_model-1.0.65.dist-info/top_level.txt
