Metadata-Version: 2.0
Name: azureml-contrib-explain-model
Version: 1.0.65
Summary: UNKNOWN
Home-page: https://docs.microsoft.com/en-us/azure/machine-learning/service/
Author: Microsoft Corp
License: Proprietary https://aka.ms/azureml-preview-sdk-license 
Platform: UNKNOWN
Provides-Extra: han
Provides-Extra: lime
Requires-Dist: azureml-explain-model (==1.0.65.*)
Provides-Extra: han
Requires-Dist: spacy; extra == 'han'
Requires-Dist: gensim; extra == 'han'
Requires-Dist: tensorflow; extra == 'han'
Provides-Extra: lime
Requires-Dist: lime; extra == 'lime'
